caskade/__init__.py
caskade/_version.py
caskade/backend.py
caskade/base.py
caskade/collection.py
caskade/context.py
caskade/decorators.py
caskade/errors.py
caskade/module.py
caskade/param.py
caskade/tests.py
caskade/warnings.py
caskade-0.14.1.dist-info/METADATA
caskade-0.14.1.dist-info/WHEEL
caskade-0.14.1.dist-info/licenses/LICENSE
caskade-0.14.1.dist-info/RECORD
