Metadata-Version: 2.4
Name: caskade
Version: 0.14.1
Summary: Package for building scientific simulators, with dynamic arguments arranged in a directed acyclic graph.
Project-URL: Homepage, https://github.com/ConnorStoneAstro/caskade
Project-URL: Documentation, https://github.com/ConnorStoneAstro/caskade
Project-URL: Repository, https://github.com/ConnorStoneAstro/caskade
Project-URL: Issues, https://github.com/ConnorStoneAstro/caskade/issues
Author-email: Connor Stone <connorstone628@gmail.com>, Alexandre Adam <alexandre.adam@mila.quebec>
License: MIT License
License-File: LICENSE
Keywords: DAG,caskade,differentiable programming,pytorch,scientific python
Classifier: Development Status :: 1 - Planning
Classifier: Intended Audience :: Science/Research
Classifier: License :: OSI Approved :: MIT License
Classifier: Operating System :: OS Independent
Classifier: Programming Language :: Python :: 3
Requires-Python: >=3.9
Requires-Dist: numpy<2,>1.22
Requires-Dist: torch<3,>=2
Provides-Extra: dev
Requires-Dist: graphviz<1,>=0.17; extra == 'dev'
Requires-Dist: h5py<4,>=3.11; extra == 'dev'
Requires-Dist: jax; extra == 'dev'
Requires-Dist: jaxlib; extra == 'dev'
Requires-Dist: pre-commit<4,>=3.6; extra == 'dev'
Requires-Dist: pytest-cov<5,>=4.1; extra == 'dev'
Requires-Dist: pytest-mock<4,>=3.12; extra == 'dev'
Requires-Dist: pytest<9,>=8.0; extra == 'dev'
Provides-Extra: jax
Requires-Dist: jax; extra == 'jax'
Requires-Dist: jaxlib; extra == 'jax'
Provides-Extra: numpy
Provides-Extra: object
Provides-Extra: torch
